QitianXuehuiDuanxianChaoguJiqiao/README.md
QitianXuehuiDuanxianChaoguJiqiao/__init__.py
QitianXuehuiDuanxianChaoguJiqiao/__main__.py
QitianXuehuiDuanxianChaoguJiqiao/file.epub
QitianXuehuiDuanxianChaoguJiqiao/index.html
QitianXuehuiDuanxianChaoguJiqiao/css/__init__.py
QitianXuehuiDuanxianChaoguJiqiao/css/annotations.css
QitianXuehuiDuanxianChaoguJiqiao/css/main.css
QitianXuehuiDuanxianChaoguJiqiao/css/normalize.css
QitianXuehuiDuanxianChaoguJiqiao/css/popup.css
QitianXuehuiDuanxianChaoguJiqiao/font/__init__.py
QitianXuehuiDuanxianChaoguJiqiao/font/fontello.eot
QitianXuehuiDuanxianChaoguJiqiao/font/fontello.svg
QitianXuehuiDuanxianChaoguJiqiao/font/fontello.ttf
QitianXuehuiDuanxianChaoguJiqiao/font/fontello.woff
QitianXuehuiDuanxianChaoguJiqiao/img/__init__.py
QitianXuehuiDuanxianChaoguJiqiao/img/annotator-glyph-sprite.png
QitianXuehuiDuanxianChaoguJiqiao/img/annotator-icon-sprite.png
QitianXuehuiDuanxianChaoguJiqiao/img/apple-touch-icon.png
QitianXuehuiDuanxianChaoguJiqiao/img/cancelfullscreen.png
QitianXuehuiDuanxianChaoguJiqiao/img/close.png
QitianXuehuiDuanxianChaoguJiqiao/img/fullscreen.png
QitianXuehuiDuanxianChaoguJiqiao/img/loader.gif
QitianXuehuiDuanxianChaoguJiqiao/img/menu-icon.png
QitianXuehuiDuanxianChaoguJiqiao/img/save.png
QitianXuehuiDuanxianChaoguJiqiao/img/saved.png
QitianXuehuiDuanxianChaoguJiqiao/img/settings-s.png
QitianXuehuiDuanxianChaoguJiqiao/img/settings.png
QitianXuehuiDuanxianChaoguJiqiao/img/star.png
QitianXuehuiDuanxianChaoguJiqiao/js/__init__.py
QitianXuehuiDuanxianChaoguJiqiao/js/epub.js
QitianXuehuiDuanxianChaoguJiqiao/js/epub.min.js
QitianXuehuiDuanxianChaoguJiqiao/js/epub.min.map
QitianXuehuiDuanxianChaoguJiqiao/js/hooks.min.js
QitianXuehuiDuanxianChaoguJiqiao/js/hooks.min.map
QitianXuehuiDuanxianChaoguJiqiao/js/reader.js
QitianXuehuiDuanxianChaoguJiqiao/js/reader.js.map
QitianXuehuiDuanxianChaoguJiqiao/js/reader.min.js
QitianXuehuiDuanxianChaoguJiqiao/js/reader.min.map
QitianXuehuiDuanxianChaoguJiqiao/js/hooks/__init__.py
qitian_xuehui_duanxian_chaogu_jiqiao-2022.10.15.0.dist-info/METADATA
qitian_xuehui_duanxian_chaogu_jiqiao-2022.10.15.0.dist-info/WHEEL
qitian_xuehui_duanxian_chaogu_jiqiao-2022.10.15.0.dist-info/entry_points.txt
qitian_xuehui_duanxian_chaogu_jiqiao-2022.10.15.0.dist-info/top_level.txt
qitian_xuehui_duanxian_chaogu_jiqiao-2022.10.15.0.dist-info/RECORD
